propeller_design_tool/__init__.py
propeller_design_tool/airfoil.py
propeller_design_tool/custom_opengl_classes.py
propeller_design_tool/foil_ui_classes.py
propeller_design_tool/funcs.py
propeller_design_tool/helper_ui_classes.py
propeller_design_tool/helper_ui_subclasses.py
propeller_design_tool/opt_ui_classes.py
propeller_design_tool/optimizations.py
propeller_design_tool/prop_analysis_ui_classes.py
propeller_design_tool/prop_creation_ui_classes.py
propeller_design_tool/propeller.py
propeller_design_tool/radialstation.py
propeller_design_tool/science_spinbox_class.py
propeller_design_tool/settings.py
propeller_design_tool/user_interface.py
propeller_design_tool/user_io.py
propeller_design_tool/foil_database/arad13.dat
propeller_design_tool/foil_database/clarky.dat
propeller_design_tool/foil_database/e855.dat
propeller_design_tool/foil_database/hs1606.dat
propeller_design_tool/foil_database/mrc-16.dat
propeller_design_tool/foil_database/xfoil.exe
propeller_design_tool/prop_database/xrotor.exe
propeller_design_tool/prop_database/MyPropeller/MyPropeller.meta
propeller_design_tool/prop_database/MyPropeller/MyPropeller.xrop
propeller_design_tool/prop_database/MyPropeller/MyPropeller.xrr
propeller_design_tool/prop_database/MyPropeller/blade_profiles/profile_0.txt
propeller_design_tool/prop_database/MyPropeller/blade_profiles/profile_1.txt
propeller_design_tool/prop_database/MyPropeller/blade_profiles/profile_10.txt
propeller_design_tool/prop_database/MyPropeller/blade_profiles/profile_11.txt
propeller_design_tool/prop_database/MyPropeller/blade_profiles/profile_12.txt
propeller_design_tool/prop_database/MyPropeller/blade_profiles/profile_13.txt
propeller_design_tool/prop_database/MyPropeller/blade_profiles/profile_14.txt
propeller_design_tool/prop_database/MyPropeller/blade_profiles/profile_15.txt
propeller_design_tool/prop_database/MyPropeller/blade_profiles/profile_16.txt
propeller_design_tool/prop_database/MyPropeller/blade_profiles/profile_17.txt
propeller_design_tool-0.0.2.dist-info/LICENSE
propeller_design_tool-0.0.2.dist-info/METADATA
propeller_design_tool-0.0.2.dist-info/WHEEL
propeller_design_tool-0.0.2.dist-info/top_level.txt
propeller_design_tool-0.0.2.dist-info/RECORD
