Metadata-Version: 2.1
Name: propeller-design-tool
Version: 0.0.2
Summary: Utilities for initial-stages of propeller design (automates usage of XFOIL and XROTOR executables).
Home-page: https://github.com/helloDestroyerOfWorlds/propeller_design_tool.git
Author: Jacob Bronson
Author-email: jakebronson89@gmail.com
Project-URL: Bug Tracker, https://github.com/helloDestroyerOfWorlds/propeller_design_tool/issues
Classifier: Development Status :: 2 - Pre-Alpha
Classifier: Intended Audience :: Science/Research
Classifier: License :: OSI Approved :: GNU General Public License v3 (GPLv3)
Classifier: Natural Language :: English
Classifier: Programming Language :: Python :: 3
Classifier: Operating System :: Microsoft :: Windows
Classifier: Topic :: Scientific/Engineering
Requires-Python: >=3.6
License-File: LICENSE
Requires-Dist: numpy >=1.21.2
Requires-Dist: matplotlib >=3.4.3
Requires-Dist: scipy >=1.7.1
Requires-Dist: numpy-stl >=2.16.3
Requires-Dist: pyqtgraph >=0.12.4
Requires-Dist: pyopengl >=3.1.6
